Workbook

Sheet Forecast Assumptions
B1: Forecast Assumptions
B3: Dec-YE | C3: Unit | D3: 43830 | E3: =EOMONTH(D3,12) -> 44196 | F3: =EOMONTH(E3,12) -> 44561 | G3: =EOMONTH(F3,12) -> 44926 | H3: =EOMONTH(G3,12) -> 45291 | I3: =EOMONTH(H3,12) -> 45657
A5: * | B5: Revenue
B7: Cupcakes
B8: Number of Units Sold | C8: # | E8: 100000 | F8: =E8*1.1 -> 110000 | G8: =F8*1.09 -> 119900 | H8: =G8*1.08 -> 129492 | I8: =H8*1.07 -> 138556.44
B9: Average Sale Price | C9: $ | E9: 4 | F9: =E9*1.04 -> 4.16 | G9: =F9*1.04 -> 4.3264 | H9: =G9*1.04 -> 4.499456 | I9: =H9*1.04 -> 4.6794342
B11: Ice Cream
B12: Number of Units Sold | C12: # | E12: 60000 | F12: =E12*1.1 -> 66000 | G12: =F12*1.09 -> 71940 | H12: =G12*1.08 -> 77695.2 | I12: =H12*1.07 -> 83133.864
B13: Average Sale Price | C13: $ | E13: 3 | F13: =E13*1.04 -> 3.12 | G13: =F13*1.04 -> 3.2448 | H13: =G13*1.04 -> 3.374592 | I13: =H13*1.04 -> 3.5095757
B15: Drinks
B16: Number of Units Sold | C16: # | E16: 50000 | F16: =E16*1.1 -> 55000 | G16: =F16*1.09 -> 59950 | H16: =G16*1.08 -> 64746 | I16: =H16*1.07 -> 69278.22
B17: Average Sale Price | C17: $ | E17: 2.5 | F17: =E17*1.04 -> 2.6 | G17: =F17*1.04 -> 2.704 | H17: =G17*1.04 -> 2.81216 | I17: =H17*1.04 -> 2.9246464
A19: * | B19: Costs
B21: Cost of Goods Sold (COGS)
B22: COGS per Cupcake | C22: $ | E22: 1.5 | F22: =E22*1.02 -> 1.53 | G22: =F22*1.02 -> 1.5606 | H22: =G22*1.02 -> 1.591812 | I22: =H22*1.02 -> 1.6236482
B23: COGS per Ice Cream | C23: $ | E23: 0.8 | F23: =E23*1.02 -> 0.816 | G23: =F23*1.02 -> 0.83232 | H23: =G23*1.02 -> 0.8489664 | I23: =H23*1.02 -> 0.86594573
B24: COGS per Drink | C24: $ | E24: 1.1 | F24: =E24*1.02 -> 1.122 | G24: =F24*1.02 -> 1.14444 | H24: =G24*1.02 -> 1.1673288 | I24: =H24*1.02 -> 1.1906754
B26: Operating Expenses (OpEx)
B27: Staff Costs | C27: $ | E27: 150000 | F27: =E27*1.05 -> 157500 | G27: =F27*1.05 -> 165375 | H27: =G27*1.05 -> 173643.75 | I27: =H27*1.05 -> 182325.94
B28: Occupancy Costs | C28: $ | E28: 60000 | F28: =E28*1.03 -> 61800 | G28: =F28*1.03 -> 63654 | H28: =G28*1.03 -> 65563.62 | I28: =H28*1.03 -> 67530.529
B29: Marketing Costs | C29: $ | E29: 10000 | F29: =E29*1.05 -> 10500 | G29: =F29*1.05 -> 11025 | H29: =G29*1.05 -> 11576.25 | I29: =H29*1.05 -> 12155.062
B30: Other Costs | C30: $ | E30: 5000 | F30: =E30*1.05 -> 5250 | G30: =F30*1.05 -> 5512.5 | H30: =G30*1.05 -> 5788.125 | I30: =H30*1.05 -> 6077.5312
B32: Depreciation & Amortization (D&A)
B33: Annual D&A | C33: % of revenue | E33: -0.05 | F33: =E33+0.25% -> -0.0475 | G33: =F33+0.25% -> -0.045 | H33: =G33+0.25% -> -0.0425 | I33: =H33+0.25% -> -0.04
A35: * | B35: Cash Flow
B37: Net Capital Expenditure (Capex) | C37: % of revenue | E37: =E33 -> -0.05 | F37: =F33 -> -0.0475 | G37: =G33 -> -0.045 | H37: =H33 -> -0.0425 | I37: =I33 -> -0.04
B38: Change in Net Working Capital (NWC) | C38: % of revenue | E38: -0.01 | F38: -0.01 | G38: -0.01 | H38: -0.01 | I38: -0.01
B39: Dividend Payout Ratio | C39: % | E39: 0.6 | F39: 0.6 | G39: 0.6 | H39: 0.6 | I39: 0.6
A41: * | B41: Other
B43: Tax Rate | C43: % | E43: 0.21 | F43: 0.21 | G43: 0.21 | H43: 0.21 | I43: 0.21
B44: Debt Interest Rate | C44: % | E44: 0.04 | F44: 0.04 | G44: 0.04 | H44: 0.04 | I44: 0.04
B45: Cash Interest Rate | C45: % | E45: 0.01 | F45: 0.01 | G45: 0.01 | H45: 0.01 | I45: 0.01
A47: * | B47: END

Sheet P&L Forecast
B1: P&L Forecast
B3: Dec-YE | C3: Unit | D3: 43830 | E3: =EOMONTH(D3,12) -> 44196 | F3: =EOMONTH(E3,12) -> 44561 | G3: =EOMONTH(F3,12) -> 44926 | H3: =EOMONTH(G3,12) -> 45291 | I3: =EOMONTH(H3,12) -> 45657
B5: Cupcakes Revenue | C5: $ | E5: ='[1]Forecast Assumptions'!E8*'[1]Forecast Assumptions'!E9 -> 400000 | F5: ='[1]Forecast Assumptions'!F8*'[1]Forecast Assumptions'!F9 -> 457600 | G5: ='[1]Forecast Assumptions'!G8*'[1]Forecast Assumptions'!G9 -> 518735.36 | H5: ='[1]Forecast Assumptions'!H8*'[1]Forecast Assumptions'!H9 -> 582643.56 | I5: ='[1]Forecast Assumptions'!I8*'[1]Forecast Assumptions'!I9 -> 648365.75
B6: Ice Cream Revenue | C6: $ | E6: ='[1]Forecast Assumptions'!E12*'[1]Forecast Assumptions'!E13 -> 180000 | F6: ='[1]Forecast Assumptions'!F12*'[1]Forecast Assumptions'!F13 -> 205920 | G6: ='[1]Forecast Assumptions'!G12*'[1]Forecast Assumptions'!G13 -> 233430.91 | H6: ='[1]Forecast Assumptions'!H12*'[1]Forecast Assumptions'!H13 -> 262189.6 | I6: ='[1]Forecast Assumptions'!I12*'[1]Forecast Assumptions'!I13 -> 291764.59
B7: Drinks Revenue | C7: $ | E7: ='[1]Forecast Assumptions'!E16*'[1]Forecast Assumptions'!E17 -> 125000 | F7: ='[1]Forecast Assumptions'!F16*'[1]Forecast Assumptions'!F17 -> 143000 | G7: ='[1]Forecast Assumptions'!G16*'[1]Forecast Assumptions'!G17 -> 162104.8 | H7: ='[1]Forecast Assumptions'!H16*'[1]Forecast Assumptions'!H17 -> 182076.11 | I7: ='[1]Forecast Assumptions'!I16*'[1]Forecast Assumptions'!I17 -> 202614.3
B8: Total Revenue | C8: $ | E8: =SUM(E5:E7) -> 705000 | F8: =SUM(F5:F7) -> 806520 | G8: =SUM(G5:G7) -> 914271.07 | H8: =SUM(H5:H7) -> 1026909.3 | I8: =SUM(I5:I7) -> 1142744.6
B9: Growth | C9: % | F9: =F8/E8-1 -> 0.144 | G9: =G8/F8-1 -> 0.1336 | H9: =H8/G8-1 -> 0.1232 | I9: =I8/H8-1 -> 0.1128
B11: Cupcakes COGS | C11: $ | E11: =-'[1]Forecast Assumptions'!E8*'[1]Forecast Assumptions'!E22 -> -150000 | F11: =-'[1]Forecast Assumptions'!F8*'[1]Forecast Assumptions'!F22 -> -168300 | G11: =-'[1]Forecast Assumptions'!G8*'[1]Forecast Assumptions'!G22 -> -187115.94 | H11: =-'[1]Forecast Assumptions'!H8*'[1]Forecast Assumptions'!H22 -> -206126.92 | I11: =-'[1]Forecast Assumptions'!I8*'[1]Forecast Assumptions'!I22 -> -224966.92
B12: Ice Cream COGS | C12: $ | E12: =-'[1]Forecast Assumptions'!E12*'[1]Forecast Assumptions'!E23 -> -48000 | F12: =-'[1]Forecast Assumptions'!F12*'[1]Forecast Assumptions'!F23 -> -53856 | G12: =-'[1]Forecast Assumptions'!G12*'[1]Forecast Assumptions'!G23 -> -59877.101 | H12: =-'[1]Forecast Assumptions'!H12*'[1]Forecast Assumptions'!H23 -> -65960.614 | I12: =-'[1]Forecast Assumptions'!I12*'[1]Forecast Assumptions'!I23 -> -71989.414
B13: Drinks COGS | C13: $ | E13: =-'[1]Forecast Assumptions'!E16*'[1]Forecast Assumptions'!E24 -> -55000 | F13: =-'[1]Forecast Assumptions'!F16*'[1]Forecast Assumptions'!F24 -> -61710 | G13: =-'[1]Forecast Assumptions'!G16*'[1]Forecast Assumptions'!G24 -> -68609.178 | H13: =-'[1]Forecast Assumptions'!H16*'[1]Forecast Assumptions'!H24 -> -75579.87 | I13: =-'[1]Forecast Assumptions'!I16*'[1]Forecast Assumptions'!I24 -> -82487.871
B14: Gross Profit | C14: $ | E14: =SUM(E8,E11:E13) -> 452000 | F14: =SUM(F8,F11:F13) -> 522654 | G14: =SUM(G8,G11:G13) -> 598668.85 | H14: =SUM(H8,H11:H13) -> 679241.86 | I14: =SUM(I8,I11:I13) -> 763300.43
B15: Margin | C15: % | E15: =E14/E$8 -> 0.64113475 | F15: =F14/F$8 -> 0.64803601 | G15: =G14/G$8 -> 0.65480454 | H15: =H14/H$8 -> 0.66144292 | I15: =I14/I$8 -> 0.66795363
B17: Staff Costs | C17: $ | E17: =-'[1]Forecast Assumptions'!E27 -> -150000 | F17: =-'[1]Forecast Assumptions'!F27 -> -157500 | G17: =-'[1]Forecast Assumptions'!G27 -> -165375 | H17: =-'[1]Forecast Assumptions'!H27 -> -173643.75 | I17: =-'[1]Forecast Assumptions'!I27 -> -182325.94
B18: Occupancy Costs | C18: $ | E18: =-'[1]Forecast Assumptions'!E28 -> -60000 | F18: =-'[1]Forecast Assumptions'!F28 -> -61800 | G18: =-'[1]Forecast Assumptions'!G28 -> -63654 | H18: =-'[1]Forecast Assumptions'!H28 -> -65563.62 | I18: =-'[1]Forecast Assumptions'!I28 -> -67530.529
B19: Marketing Costs | C19: $ | E19: =-'[1]Forecast Assumptions'!E29 -> -10000 | F19: =-'[1]Forecast Assumptions'!F29 -> -10500 | G19: =-'[1]Forecast Assumptions'!G29 -> -11025 | H19: =-'[1]Forecast Assumptions'!H29 -> -11576.25 | I19: =-'[1]Forecast Assumptions'!I29 -> -12155.062
B20: Other Costs | C20: $ | E20: =-'[1]Forecast Assumptions'!E30 -> -5000 | F20: =-'[1]Forecast Assumptions'!F30 -> -5250 | G20: =-'[1]Forecast Assumptions'!G30 -> -5512.5 | H20: =-'[1]Forecast Assumptions'!H30 -> -5788.125 | I20: =-'[1]Forecast Assumptions'!I30 -> -6077.5312
B21: EBITDA | C21: $ | E21: =SUM(E14,E17:E20) -> 227000 | F21: =SUM(F14,F17:F20) -> 287604 | G21: =SUM(G14,G17:G20) -> 353102.35 | H21: =SUM(H14,H17:H20) -> 422670.12 | I21: =SUM(I14,I17:I20) -> 495211.37
B22: Margin | C22: % | E22: =E21/E$8 -> 0.32198582 | F22: =F21/F$8 -> 0.35659872 | G22: =G21/G$8 -> 0.38621188 | H22: =H21/H$8 -> 0.41159441 | I22: =I21/I$8 -> 0.43335261
B24: D&A | C24: $ | E24: ='[1]Forecast Assumptions'!E33*E8 -> -35250 | F24: ='[1]Forecast Assumptions'!F33*F8 -> -38309.7 | G24: ='[1]Forecast Assumptions'!G33*G8 -> -41142.198 | H24: ='[1]Forecast Assumptions'!H33*H8 -> -43643.644 | I24: ='[1]Forecast Assumptions'!I33*I8 -> -45709.785
B25: EBIT (Operating Income) | C25: $ | E25: =SUM(E21,E24) -> 191750 | F25: =SUM(F21,F24) -> 249294.3 | G25: =SUM(G21,G24) -> 311960.15 | H25: =SUM(H21,H24) -> 379026.47 | I25: =SUM(I21,I24) -> 449501.58
B26: Margin | C26: % | E26: =E25/E$8 -> 0.27198582 | F26: =F25/F$8 -> 0.30909872 | G26: =G25/G$8 -> 0.34121188 | H26: =H25/H$8 -> 0.36909441 | I26: =I25/I$8 -> 0.39335261
B28: Net Interest | C28: $ | E28: ='Cash Flow Forecast'!E10 -> -15850 | F28: ='Cash Flow Forecast'!F10 -> -13908.624 | G28: ='Cash Flow Forecast'!G10 -> -11255.957 | H28: ='Cash Flow Forecast'!H10 -> -7820.7644 | I28: ='Cash Flow Forecast'!I10 -> -3539.4879
B29: Profit Before Tax (PBT) | C29: $ | E29: =SUM(E25,E28) -> 175900 | F29: =SUM(F25,F28) -> 235385.68 | G29: =SUM(G25,G28) -> 300704.2 | H29: =SUM(H25,H28) -> 371205.71 | I29: =SUM(I25,I28) -> 445962.1
B30: Margin | C30: % | E30: =E29/E$8 -> 0.24950355 | F30: =F29/F$8 -> 0.29185349 | G30: =G29/G$8 -> 0.32890048 | H30: =H29/H$8 -> 0.36147859 | I30: =I29/I$8 -> 0.39025525
B32: Tax Expense | C32: $ | E32: =-'[1]Forecast Assumptions'!E43*'P&L Forecast'!E29 -> -36939 | F32: =-'[1]Forecast Assumptions'!F43*'P&L Forecast'!F29 -> -49430.992 | G32: =-'[1]Forecast Assumptions'!G43*'P&L Forecast'!G29 -> -63147.882 | H32: =-'[1]Forecast Assumptions'!H43*'P&L Forecast'!H29 -> -77953.199 | I32: =-'[1]Forecast Assumptions'!I43*'P&L Forecast'!I29 -> -93652.04
B33: Net Profit After Tax (NPAT) | C33: $ | E33: =SUM(E29,E32) -> 138961 | F33: =SUM(F29,F32) -> 185954.68 | G33: =SUM(G29,G32) -> 237556.32 | H33: =SUM(H29,H32) -> 293252.51 | I33: =SUM(I29,I32) -> 352310.06
B34: Margin | C34: % | E34: =E33/E$8 -> 0.1971078 | F34: =F33/F$8 -> 0.23056426 | G34: =G33/G$8 -> 0.25983138 | H34: =H33/H$8 -> 0.28556808 | I34: =I33/I$8 -> 0.30830165
B36: Dividend Payout Ratio | C36: % | E36: ='[1]Forecast Assumptions'!E39 -> 0.6 | F36: ='[1]Forecast Assumptions'!F39 -> 0.6 | G36: ='[1]Forecast Assumptions'!G39 -> 0.6 | H36: ='[1]Forecast Assumptions'!H39 -> 0.6 | I36: ='[1]Forecast Assumptions'!I39 -> 0.6
B37: Gross Dividends | C37: $ | E37: =E33*E36 -> 83376.6 | F37: =F33*F36 -> 111572.81 | G37: =G33*G36 -> 142533.79 | H37: =H33*H36 -> 175951.51 | I37: =I33*I36 -> 211386.03
A39: * | B39: END

Sheet Cash Flow Forecast
B1: Cash Flow Forecast
B3: Dec-YE | C3: Unit | D3: 43830 | E3: =EOMONTH(D3,12) -> 44196 | F3: =EOMONTH(E3,12) -> 44561 | G3: =EOMONTH(F3,12) -> 44926 | H3: =EOMONTH(G3,12) -> 45291 | I3: =EOMONTH(H3,12) -> 45657
B5: EBITDA | C5: $ | E5: 227000 | F5: 287604 | G5: 353102.35 | H5: 422670.12 | I5: 495211.37
B6: Tax Expense | C6: $ | E6: ='[1]P&L Forecast'!E32 -> -36939 | F6: ='[1]P&L Forecast'!F32 -> -49430.992 | G6: ='[1]P&L Forecast'!G32 -> -63147.882 | H6: ='[1]P&L Forecast'!H32 -> -77953.199 | I6: ='[1]P&L Forecast'!I32 -> -93652.04
B7: Changes in NWC | C7: $ | E7: ='[1]P&L Forecast'!E8*'[1]Forecast Assumptions'!E38 -> -7050 | F7: ='[1]P&L Forecast'!F8*'[1]Forecast Assumptions'!F38 -> -8065.2 | G7: ='[1]P&L Forecast'!G8*'[1]Forecast Assumptions'!G38 -> -9142.7107 | H7: ='[1]P&L Forecast'!H8*'[1]Forecast Assumptions'!H38 -> -10269.093 | I7: ='[1]P&L Forecast'!I8*'[1]Forecast Assumptions'!I38 -> -11427.446
B8: Net Capex | C8: $ | E8: ='[1]P&L Forecast'!E8*'[1]Forecast Assumptions'!E37 -> -35250 | F8: ='[1]P&L Forecast'!F8*'[1]Forecast Assumptions'!F37 -> -38309.7 | G8: ='[1]P&L Forecast'!G8*'[1]Forecast Assumptions'!G37 -> -41142.198 | H8: ='[1]P&L Forecast'!H8*'[1]Forecast Assumptions'!H37 -> -43643.644 | I8: ='[1]P&L Forecast'!I8*'[1]Forecast Assumptions'!I37 -> -45709.785
B9: Dividends | C9: $ | E9: ='[1]P&L Forecast'!E37*-1 -> -83376.6 | F9: ='[1]P&L Forecast'!F37*-1 -> -111572.81 | G9: ='[1]P&L Forecast'!G37*-1 -> -142533.79 | H9: ='[1]P&L Forecast'!H37*-1 -> -175951.51 | I9: ='[1]P&L Forecast'!I37*-1 -> -211386.03
B10: Net Interest | C10: $ | E10: =-1*(E21*'[1]Forecast Assumptions'!$E$44)+('Cash Flow Forecast'!E15*'[1]Forecast Assumptions'!$E$45) -> -15850 | F10: =-1*(F21*'[1]Forecast Assumptions'!$E$44)+('Cash Flow Forecast'!F15*'[1]Forecast Assumptions'!$E$45) -> -13908.624 | G10: =-1*(G21*'[1]Forecast Assumptions'!$E$44)+('Cash Flow Forecast'!G15*'[1]Forecast Assumptions'!$E$45) -> -11255.957 | H10: =-1*(H21*'[1]Forecast Assumptions'!$E$44)+('Cash Flow Forecast'!H15*'[1]Forecast Assumptions'!$E$45) -> -7820.7644 | I10: =-1*(I21*'[1]Forecast Assumptions'!$E$44)+('Cash Flow Forecast'!I15*'[1]Forecast Assumptions'!$E$45) -> -3539.4879
B11: Net Cash Flow | C11: $ | E11: =SUM(E5:E10) -> 48534.4 | F11: =SUM(F5:F10) -> 66316.674 | G11: =SUM(G5:G10) -> 85879.816 | H11: =SUM(H5:H10) -> 107031.91 | I11: =SUM(I5:I10) -> 129496.58
B12: Debt Repayment | C12: $ | E12: =-MIN(E11,E21) -> -48534.4 | F12: =-MIN(F11,F21) -> -66316.674 | G12: =-MIN(G11,G21) -> -85879.816 | H12: =-MIN(H11,H21) -> -107031.91 | I12: =-MIN(I11,I21) -> -92237.199
B13: Cash to Balance Sheet | C13: $ | E13: =SUM(E11:E12) -> 0 | F13: =SUM(F11:F12) -> 0 | G13: =SUM(G11:G12) -> 0 | H13: =SUM(H11:H12) -> 0 | I13: =SUM(I11:I12) -> 37259.377
B15: Opening Cash | C15: $ | E15: =D17 -> 15000 | F15: =E17 -> 15000 | G15: =F17 -> 15000 | H15: =G17 -> 15000 | I15: =H17 -> 15000
B16: Cash to Balance Sheet | C16: $
B17: Closing Cash | C17: $ | D17: 15000 | E17: =SUM(E15:E16) -> 15000 | F17: =SUM(F15:F16) -> 15000 | G17: =SUM(G15:G16) -> 15000 | H17: =SUM(H15:H16) -> 15000 | I17: =SUM(I15:I16) -> 15000
A19: * | B19: Supporting Debt Schedule
B21: Opening Debt | C21: $ | E21: =D23 -> 400000 | F21: =E23 -> 351465.6 | G21: =F23 -> 285148.93 | H21: =G23 -> 199269.11 | I21: =H23 -> 92237.199
B22: Debt Repayment | C22: $ | E22: =E12 -> -48534.4 | F22: =F12 -> -66316.674 | G22: =G12 -> -85879.816 | H22: =H12 -> -107031.91 | I22: =I12 -> -92237.199
B23: Closing Debt | C23: $ | D23: 400000 | E23: =SUM(E21:E22) -> 351465.6 | F23: =SUM(F21:F22) -> 285148.93 | G23: =SUM(G21:G22) -> 199269.11 | H23: =SUM(H21:H22) -> 92237.199 | I23: =SUM(I21:I22) -> 0
A25: * | B25: END

Sheet Outputs
B1: Outputs
B3: Example Chart (Cupcake Volume - 2020-24)
B31: Forecast Revenue (2020-24) - Column Chart
B59: Forecast Debt (2020-24) - Line Chart
B87: Forecast Cash (2020-24) - Area Chart
B115: Cupcakes Operating Metrics (2020-24) - Combination Column & Line Chart
